{"FishesInFight":[{"locker":{},"dt":{"Dispatcher":{"Thread":{"ManagedThreadId":1,"IsAlive":true,"IsBackground":false,"IsThreadPoolThread":false,"Priority":2,"ThreadState":0,"CurrentCulture":"en-US","CurrentUICulture":"en-US","ExecutionContext":{},"Name":null,"ApartmentState":0},"HasShutdownStarted":false,"HasShutdownFinished":false,"Hooks":{}},"IsEnabled":false,"Interval":"00:00:00.0010000","Tag":null},"vegzo":{"Dispatcher":{"Thread":{"ManagedThreadId":1,"IsAlive":true,"IsBackground":false,"IsThreadPoolThread":false,"Priority":2,"ThreadState":0,"CurrentCulture":"en-US","CurrentUICulture":"en-US","ExecutionContext":{},"Name":null,"ApartmentState":0},"HasShutdownStarted":false,"HasShutdownFinished":false,"Hooks":{}},"IsEnabled":false,"Interval":"00:00:00.1000000","Tag":null},"Elet":130,"Ero":10,"Level":0,"EXP":0,"Maxhp":100,"delegalthozzaadva":false,"lovedeke":{"x":0.0,"y":0.0,"aktiv":false,"eleres":"bubble.png","Sebesseg":"0,0"},"Tavolsagi":null,"Buff":null,"Eleresiut":"fishmodel.png","elfoglalt":false,"sorszam":2,"pozicio":30,"meghalt":false,"x":0.0,"y":0.0,"oldx":0.0,"oldy":0.0,"tamad":false,"visszamegy":false,"Kozelsebzes":10,"Helye":2,"regieleres":"fishmodel.png","csikmutat":true,"dead":"fishbone.png","Kepessegeffekt":"no"},{"locker":{},"dt":{"Dispatcher":{"Thread":{"ManagedThreadId":1,"IsAlive":true,"IsBackground":false,"IsThreadPoolThread":false,"Priority":2,"ThreadState":0,"CurrentCulture":"en-US","CurrentUICulture":"en-US","ExecutionContext":{},"Name":null,"ApartmentState":0},"HasShutdownStarted":false,"HasShutdownFinished":false,"Hooks":{}},"IsEnabled":false,"Interval":"00:00:00.0010000","Tag":null},"vegzo":{"Dispatcher":{"Thread":{"ManagedThreadId":1,"IsAlive":true,"IsBackground":false,"IsThreadPoolThread":false,"Priority":2,"ThreadState":0,"CurrentCulture":"en-US","CurrentUICulture":"en-US","ExecutionContext":{},"Name":null,"ApartmentState":0},"HasShutdownStarted":false,"HasShutdownFinished":false,"Hooks":{}},"IsEnabled":false,"Interval":"00:00:00.1000000","Tag":null},"Elet":150,"Ero":10,"Level":0,"EXP":0,"Maxhp":100,"delegalthozzaadva":false,"lovedeke":{"x":0.0,"y":0.0,"aktiv":false,"eleres":"bubble.png","Sebesseg":"0,0"},"Tavolsagi":null,"Buff":null,"Eleresiut":"fishmodel.png","elfoglalt":false,"sorszam":2,"pozicio":30,"meghalt":false,"x":0.0,"y":0.0,"oldx":0.0,"oldy":0.0,"tamad":false,"visszamegy":false,"Kozelsebzes":10,"Helye":2,"regieleres":"fishmodel.png","csikmutat":true,"dead":"fishbone.png","Kepessegeffekt":"no"},{"locker":{},"dt":{"Dispatcher":{"Thread":{"ManagedThreadId":1,"IsAlive":true,"IsBackground":false,"IsThreadPoolThread":false,"Priority":2,"ThreadState":0,"CurrentCulture":"en-US","CurrentUICulture":"en-US","ExecutionContext":{},"Name":null,"ApartmentState":0},"HasShutdownStarted":false,"HasShutdownFinished":false,"Hooks":{}},"IsEnabled":false,"Interval":"00:00:00.0010000","Tag":null},"vegzo":{"Dispatcher":{"Thread":{"ManagedThreadId":1,"IsAlive":true,"IsBackground":false,"IsThreadPoolThread":false,"Priority":2,"ThreadState":0,"CurrentCulture":"en-US","CurrentUICulture":"en-US","ExecutionContext":{},"Name":null,"ApartmentState":0},"HasShutdownStarted":false,"HasShutdownFinished":false,"Hooks":{}},"IsEnabled":false,"Interval":"00:00:00.1000000","Tag":null},"Elet":100,"Ero":10,"Level":0,"EXP":0,"Maxhp":100,"delegalthozzaadva":false,"lovedeke":{"x":0.0,"y":0.0,"aktiv":false,"eleres":"bubble.png","Sebesseg":"0,0"},"Tavolsagi":null,"Buff":null,"Eleresiut":"fishmodel.png","elfoglalt":false,"sorszam":1,"pozicio":0,"meghalt":false,"x":0.0,"y":0.0,"oldx":0.0,"oldy":0.0,"tamad":false,"visszamegy":false,"Kozelsebzes":10,"Helye":1,"regieleres":"fishmodel.png","csikmutat":true,"dead":"fishbone.png","Kepessegeffekt":"no"}],"AllFishes":[],"Level":0,"Potions":[],"SeaCoin":0,"Energy":3,"IsActive":false}